CHANGELOG.md
LICENSE
MANIFEST.in
README.md
setup.py
cellulario/__init__.py
cellulario/coordination.py
cellulario/iocell.py
cellulario/tier.py
cellulario.egg-info/PKG-INFO
cellulario.egg-info/SOURCES.txt
cellulario.egg-info/dependency_links.txt
cellulario.egg-info/top_level.txt
test/__init__.py
test/coordination.py
test/gc.py
test/iocell.py