Metadata-Version: 1.1
Name: cellulario
Version: 3.0
Summary: Cellular IO
Home-page: https://github.com/mayfield/cellulario/
Author: Justin Mayfield
Author-email: tooker@gmail.com
License: MIT
Platform: UNKNOWN
Classifier: Development Status :: 3 - Alpha
Classifier: Intended Audience :: Developers
Classifier: License :: OSI Approved :: MIT License
Classifier: Operating System :: OS Independent
Classifier: Programming Language :: Python
Classifier: Programming Language :: Python :: 3.5
Classifier: Programming Language :: Python :: 3.6
Classifier: Programming Language :: Python :: 3.7
